SVMmargin/SVMmargin.py
SVMmargin/__init__.py
SVMmargin-1.3.dist-info/LICENSE
SVMmargin-1.3.dist-info/METADATA
SVMmargin-1.3.dist-info/WHEEL
SVMmargin-1.3.dist-info/top_level.txt
SVMmargin-1.3.dist-info/RECORD
